[
{
        "appver" : "0",
        "des" : "[Update LOG]\n(0.1 Beta)\n*Release\n(1.0 Release)\n*Added 10 BGM\n*Deleted Korean Version",
        "dev" : "Blackcats4567",
        "file" : "[{\"cus10\":\"\",\"cus1\":\"\",\"code5\":\"\",\"cus4\":\"\",\"data\":\"\",\"cus8\":\"\",\"cus7\":\"\",\"cus2\":\"\",\"cus9\":\"\",\"code\":\"\\u003chead\\u003e\",\"cus3\":\"\",\"cus6\":\"\",\"cusdata\":\"\",\"code3\":\"\",\"num\":\"2\",\"cus5\":\"\",\"code4\":\"\",\"cusnum\":\"\",\"code2\":\"\"},{\"cus10\":\"\",\"cus1\":\"\",\"code5\":\"\",\"cus4\":\"\",\"data\":\"YOUTUBE BGM LIST\",\"cus8\":\"\",\"cus7\":\"\",\"cus2\":\"\",\"cus9\":\"\",\"code\":\"\\u003ctitle\\u003eYOUTUBE BGM LIST\\u003c/title\\u003e\",\"cus3\":\"\",\"cus6\":\"\",\"cusdata\":\"\",\"code3\":\"\",\"num\":\"13\",\"cus5\":\"\",\"code4\":\"\",\"cusnum\":\"\",\"code2\":\"\"},{\"cus10\":\"\",\"cus1\":\"\",\"code5\":\"\",\"cus4\":\"\",\"data\":\"\",\"cus8\":\"\",\"cus7\":\"\",\"cus2\":\"\",\"cus9\":\"\",\"code\":\"\\u003clink rel\\u003d\\\"shortcut icon\\\" href\\u003d\\\"\\\" type\\u003d\\\"image/png\\\"\\u003e\",\"cus3\":\"\",\"cus6\":\"\",\"cusdata\":\"\",\"code3\":\"\",\"num\":\"14\",\"cus5\":\"\",\"code4\":\"\",\"cusnum\":\"\",\"code2\":\"\"},{\"cus10\":\"\",\"cus1\":\"\",\"code5\":\"\",\"cus4\":\"\",\"data\":\"\",\"cus8\":\"\",\"cus7\":\"\",\"cus2\":\"\",\"cus9\":\"\",\"code\":\"\\u003c/head\\u003e\",\"cus3\":\"\",\"cus6\":\"\",\"cusdata\":\"\",\"code3\":\"\",\"num\":\"3\",\"cus5\":\"\",\"code4\":\"\",\"cusnum\":\"\",\"code2\":\"\"},{\"cus10\":\"\",\"cus1\":\"\",\"code5\":\"\",\"cus4\":\"\",\"data\":\"\",\"cus8\":\"\",\"cus7\":\"\",\"cus2\":\"\",\"cus9\":\"\",\"code\":\"\\u003cbody\\u003e\",\"cus3\":\"\",\"cus6\":\"\",\"cusdata\":\"\",\"code3\":\"\",\"num\":\"4\",\"cus5\":\"\",\"code4\":\"\",\"cusnum\":\"\",\"code2\":\"\"},{\"cus10\":\"\",\"cus1\":\"\",\"code5\":\"\",\"cus4\":\"\",\"data\":\"\\u003ch1\\u003eBGM LIST\\u003c/h1\\u003e\\u003ch3\\u003eTheFatRat - TimeLapse\\u003c/h3\\u003e\",\"cus8\":\"\",\"cus7\":\"\",\"cus2\":\"\",\"cus9\":\"\",\"code\":\"\\u003ch1\\u003eBGM LIST\\u003c/h1\\u003e\\u003ch3\\u003eTheFatRat - TimeLapse\\u003c/h3\\u003e\",\"cus3\":\"\",\"cus6\":\"\",\"cusdata\":\"\",\"code3\":\"\",\"num\":\"0\",\"cus5\":\"\",\"code4\":\"\",\"cusnum\":\"\",\"code2\":\"\"},{\"cus10\":\"\",\"cus1\":\"\",\"code5\":\"\",\"cus4\":\"\",\"cus7\":\"\",\"data\":\"Good bgm\",\"cus8\":\"\",\"cus2\":\"\",\"cus9\":\"\",\"code\":\"\\u003cfont face\\u003d\\\"\\\"\\u003e\\u003cp\\u003eGood bgm\\u003c/p\\u003e\",\"cus3\":\"\",\"cus6\":\"\",\"cusdata\":\"\",\"code3\":\"\",\"num\":\"1\",\"cus5\":\"\",\"code4\":\"\",\"code2\":\"\"},{\"cus10\":\"\",\"cus1\":\"\",\"code5\":\"\",\"cus4\":\"\",\"data\":\"\\u003caudio controls autoplay\\u003e \\u003csource src\\u003d\\\"https://bcan.kro.kr/webapp/bgmlist/TheFatRatTimeLapse.mp3\\\" type\\u003d\\\"audio/mpeg\\\"\\u003eYour browser does not support the audio element.\\u003c/audio\\u003e\",\"cus8\":\"\",\"cus7\":\"\",\"cus2\":\"\",\"cus9\":\"\",\"code\":\"\\u003caudio controls autoplay\\u003e \\u003csource src\\u003d\\\"https://bcan.kro.kr/webapp/bgmlist/TheFatRatTimeLapse.mp3\\\" type\\u003d\\\"audio/mpeg\\\"\\u003eYour browser does not support the audio element.\\u003c/audio\\u003e\",\"cus3\":\"\",\"cus6\":\"\",\"cusdata\":\"\",\"code3\":\"\",\"num\":\"0\",\"cus5\":\"\",\"code4\":\"\",\"cusnum\":\"\",\"code2\":\"\"},{\"cus10\":\"\",\"cus1\":\"\",\"code5\":\"\",\"cus4\":\"\",\"data\":\"\\u003ch3\\u003eTheFatRat - Unity\\u003c/h3\\u003e\",\"cus8\":\"\",\"cus7\":\"\",\"cus2\":\"\",\"cus9\":\"\",\"code\":\"\\u003ch3\\u003eTheFatRat - Unity\\u003c/h3\\u003e\",\"cus3\":\"\",\"cus6\":\"\",\"cusdata\":\"\",\"code3\":\"\",\"num\":\"0\",\"cus5\":\"\",\"code4\":\"\",\"cusnum\":\"\",\"code2\":\"\"},{\"cus10\":\"\",\"cus1\":\"\",\"code5\":\"\",\"cus4\":\"\",\"cus7\":\"\",\"data\":\"XD\",\"cus8\":\"\",\"cus2\":\"\",\"cus9\":\"\",\"code\":\"\\u003cfont face\\u003d\\\"\\\"\\u003e\\u003cp\\u003eXD\\u003c/p\\u003e\",\"cus3\":\"\",\"cus6\":\"\",\"cusdata\":\"\",\"code3\":\"\",\"num\":\"1\",\"cus5\":\"\",\"code4\":\"\",\"code2\":\"\"},{\"cus10\":\"\",\"cus1\":\"\",\"code5\":\"\",\"cus4\":\"\",\"data\":\"\\u003caudio controls autoplay\\u003e \\u003csource src\\u003d\\\"https://bcan.kro.kr/webapp/bgmlist/TheFatRatUnity.mp3\\\" type\\u003d\\\"audio/mpeg\\\"\\u003eYour browser does not support the audio element.\\u003c/audio\\u003e\",\"cus8\":\"\",\"cus7\":\"\",\"cus2\":\"\",\"cus9\":\"\",\"code\":\"\\u003caudio controls autoplay\\u003e \\u003csource src\\u003d\\\"https://bcan.kro.kr/webapp/bgmlist/TheFatRatUnity.mp3\\\" type\\u003d\\\"audio/mpeg\\\"\\u003eYour browser does not support the audio element.\\u003c/audio\\u003e\",\"cus3\":\"\",\"cus6\":\"\",\"cusdata\":\"\",\"code3\":\"\",\"num\":\"0\",\"cus5\":\"\",\"code4\":\"\",\"cusnum\":\"\",\"code2\":\"\"},{\"cus10\":\"\",\"code5\":\"\",\"cus1\":\"\",\"cus4\":\"\",\"cus7\":\"\",\"cus8\":\"\",\"data\":\"\\u003ch3\\u003eAlan Walker - Fade\\u003c/h3\\u003e\",\"cus2\":\"\",\"cus9\":\"\",\"code\":\"\\u003ch3\\u003eAlan Walker - Fade\\u003c/h3\\u003e\",\"cus6\":\"\",\"cusdata\":\"\",\"cus3\":\"\",\"code3\":\"\",\"num\":\"0\",\"cus5\":\"\",\"code4\":\"\",\"cusnum\":\"\",\"code2\":\"\"},{\"cus10\":\"\",\"code5\":\"\",\"cus1\":\"\",\"cus4\":\"\",\"cus7\":\"\",\"cus8\":\"\",\"data\":\"Famous song\",\"cus2\":\"\",\"cus9\":\"\",\"code\":\"\\u003cfont face\\u003d\\\"\\\"\\u003e\\u003cp\\u003eFamous song\\u003c/p\\u003e\",\"cus6\":\"\",\"cusdata\":\"\",\"cus3\":\"\",\"code3\":\"\",\"num\":\"1\",\"cus5\":\"\",\"code4\":\"\",\"code2\":\"\"},{\"cus10\":\"\",\"code5\":\"\",\"cus1\":\"\",\"cus4\":\"\",\"cus7\":\"\",\"cus8\":\"\",\"data\":\"\\u003caudio controls autoplay\\u003e \\u003csource src\\u003d\\\"https://bcan.kro.kr/webapp/bgmlist/AlanWalkerFade.mp3\\\" type\\u003d\\\"audio/mpeg\\\"\\u003eYour browser does not support the audio element.\\u003c/audio\\u003e\",\"cus2\":\"\",\"cus9\":\"\",\"code\":\"\\u003caudio controls autoplay\\u003e \\u003csource src\\u003d\\\"https://bcan.kro.kr/webapp/bgmlist/AlanWalkerFade.mp3\\\" type\\u003d\\\"audio/mpeg\\\"\\u003eYour browser does not support the audio element.\\u003c/audio\\u003e\",\"cus6\":\"\",\"cusdata\":\"\",\"cus3\":\"\",\"code3\":\"\",\"num\":\"0\",\"cus5\":\"\",\"code4\":\"\",\"cusnum\":\"\",\"code2\":\"\"},{\"cus10\":\"\",\"code5\":\"\",\"cus1\":\"\",\"cus4\":\"\",\"cus8\":\"\",\"cus7\":\"\",\"data\":\"\\u003ch3\\u003eVexento - We Are One\\u003c/h3\\u003e\",\"cus2\":\"\",\"cus9\":\"\",\"code\":\"\\u003ch3\\u003eVexento - We Are One\\u003c/h3\\u003e\",\"cusdata\":\"\",\"cus3\":\"\",\"cus6\":\"\",\"code3\":\"\",\"cus5\":\"\",\"num\":\"0\",\"code4\":\"\",\"cusnum\":\"\",\"code2\":\"\"},{\"cus10\":\"\",\"code5\":\"\",\"cus1\":\"\",\"cus4\":\"\",\"cus8\":\"\",\"cus7\":\"\",\"data\":\"GG!\",\"cus2\":\"\",\"cus9\":\"\",\"code\":\"\\u003cfont face\\u003d\\\"\\\"\\u003e\\u003cp\\u003eGG!\\u003c/p\\u003e\",\"cusdata\":\"\",\"cus3\":\"\",\"cus6\":\"\",\"code3\":\"\",\"cus5\":\"\",\"num\":\"1\",\"code4\":\"\",\"code2\":\"\"},{\"cus10\":\"\",\"code5\":\"\",\"cus1\":\"\",\"cus4\":\"\",\"cus7\":\"\",\"cus8\":\"\",\"data\":\"\\u003caudio controls autoplay\\u003e \\u003csource src\\u003d\\\"https://bcan.kro.kr/webapp/bgmlist/WeAreOneVexento.mp3\\\" type\\u003d\\\"audio/mpeg\\\"\\u003eYour browser does not support the audio element.\\u003c/audio\\u003e\",\"cus2\":\"\",\"cus9\":\"\",\"code\":\"\\u003caudio controls autoplay\\u003e \\u003csource src\\u003d\\\"https://bcan.kro.kr/webapp/bgmlist/WeAreOneVexento.mp3\\\" type\\u003d\\\"audio/mpeg\\\"\\u003eYour browser does not support the audio element.\\u003c/audio\\u003e\",\"cus3\":\"\",\"cus6\":\"\",\"cusdata\":\"\",\"code3\":\"\",\"num\":\"0\",\"cus5\":\"\",\"code4\":\"\",\"cusnum\":\"\",\"code2\":\"\"},{\"cus10\":\"\",\"code5\":\"\",\"cus1\":\"\",\"cus4\":\"\",\"cus8\":\"\",\"cus7\":\"\",\"data\":\"\\u003ch3\\u003eSilentPartner - BlueSkies\\u003c/h3\\u003e\",\"cus2\":\"\",\"cus9\":\"\",\"code\":\"\\u003ch3\\u003eSilentPartner - BlueSkies\\u003c/h3\\u003e\",\"cus6\":\"\",\"cusdata\":\"\",\"cus3\":\"\",\"code3\":\"\",\"cus5\":\"\",\"num\":\"0\",\"code4\":\"\",\"cusnum\":\"\",\"code2\":\"\"},{\"cus10\":\"\",\"code5\":\"\",\"cus1\":\"\",\"cus4\":\"\",\"cus7\":\"\",\"cus8\":\"\",\"data\":\"Where have you not heard?\",\"cus2\":\"\",\"cus9\":\"\",\"code\":\"\\u003cfont face\\u003d\\\"\\\"\\u003e\\u003cp\\u003eWhere have you not heard?\\u003c/p\\u003e\",\"cusdata\":\"\",\"cus3\":\"\",\"cus6\":\"\",\"code3\":\"\",\"num\":\"1\",\"cus5\":\"\",\"code4\":\"\",\"code2\":\"\"},{\"cus10\":\"\",\"code5\":\"\",\"cus1\":\"\",\"cus4\":\"\",\"cus7\":\"\",\"cus8\":\"\",\"data\":\"\\u003caudio controls autoplay\\u003e \\u003csource src\\u003d\\\"https://bcan.kro.kr/webapp/bgmlist/SilentPartnerBlueSkies.mp3\\\" type\\u003d\\\"audio/mpeg\\\"\\u003eYour browser does not support the audio element.\\u003c/audio\\u003e\",\"cus2\":\"\",\"cus9\":\"\",\"code\":\"\\u003caudio controls autoplay\\u003e \\u003csource src\\u003d\\\"https://bcan.kro.kr/webapp/bgmlist/SilentPartnerBlueSkies.mp3\\\" type\\u003d\\\"audio/mpeg\\\"\\u003eYour browser does not support the audio element.\\u003c/audio\\u003e\",\"cusdata\":\"\",\"cus3\":\"\",\"cus6\":\"\",\"code3\":\"\",\"num\":\"0\",\"cus5\":\"\",\"code4\":\"\",\"cusnum\":\"\",\"code2\":\"\"},{\"cus10\":\"\",\"code5\":\"\",\"cus1\":\"\",\"cus4\":\"\",\"cus7\":\"\",\"cus8\":\"\",\"data\":\"\\u003ch3\\u003eSilentPartner - SugarZone\\u003c/h3\\u003e\",\"cus2\":\"\",\"cus9\":\"\",\"code\":\"\\u003ch3\\u003eSilentPartner - SugarZone\\u003c/h3\\u003e\",\"cus6\":\"\",\"cusdata\":\"\",\"cus3\":\"\",\"code3\":\"\",\"num\":\"0\",\"cus5\":\"\",\"code4\":\"\",\"cusnum\":\"\",\"code2\":\"\"},{\"cus10\":\"\",\"code5\":\"\",\"cus1\":\"\",\"cus4\":\"\",\"cus7\":\"\",\"cus8\":\"\",\"data\":\"I know this background music!\",\"cus2\":\"\",\"cus9\":\"\",\"code\":\"\\u003cfont face\\u003d\\\"\\\"\\u003e\\u003cp\\u003eI know this background music!\\u003c/p\\u003e\",\"cus6\":\"\",\"cusdata\":\"\",\"cus3\":\"\",\"code3\":\"\",\"num\":\"1\",\"cus5\":\"\",\"code4\":\"\",\"code2\":\"\"},{\"cus10\":\"\",\"code5\":\"\",\"cus1\":\"\",\"cus4\":\"\",\"cus7\":\"\",\"cus8\":\"\",\"data\":\"\\u003caudio controls autoplay\\u003e \\u003csource src\\u003d\\\"https://bcan.kro.kr/webapp/bgmlist/SilentPartnerSugarZone.mp3\\\" type\\u003d\\\"audio/mpeg\\\"\\u003eYour browser does not support the audio element.\\u003c/audio\\u003e\",\"cus2\":\"\",\"cus9\":\"\",\"code\":\"\\u003caudio controls autoplay\\u003e \\u003csource src\\u003d\\\"https://bcan.kro.kr/webapp/bgmlist/SilentPartnerSugarZone.mp3\\\" type\\u003d\\\"audio/mpeg\\\"\\u003eYour browser does not support the audio element.\\u003c/audio\\u003e\",\"cus6\":\"\",\"cusdata\":\"\",\"cus3\":\"\",\"code3\":\"\",\"num\":\"0\",\"cus5\":\"\",\"code4\":\"\",\"cusnum\":\"\",\"code2\":\"\"},{\"cus10\":\"\",\"code5\":\"\",\"cus1\":\"\",\"cus4\":\"\",\"cus7\":\"\",\"cus8\":\"\",\"data\":\"\\u003ch3\\u003eSilentPartner - SummerSmile\\u003c/h3\\u003e\",\"cus2\":\"\",\"cus9\":\"\",\"code\":\"\\u003ch3\\u003eSilentPartner - SummerSmile\\u003c/h3\\u003e\",\"cus3\":\"\",\"cus6\":\"\",\"cusdata\":\"\",\"code3\":\"\",\"num\":\"0\",\"cus5\":\"\",\"code4\":\"\",\"cusnum\":\"\",\"code2\":\"\"},{\"cus10\":\"\",\"code5\":\"\",\"cus1\":\"\",\"cus4\":\"\",\"cus7\":\"\",\"cus8\":\"\",\"data\":\"Silent Partner 👍\",\"cus2\":\"\",\"cus9\":\"\",\"code\":\"\\u003cfont face\\u003d\\\"\\\"\\u003e\\u003cp\\u003eSilent Partner 👍\\u003c/p\\u003e\",\"cus3\":\"\",\"cus6\":\"\",\"cusdata\":\"\",\"code3\":\"\",\"num\":\"1\",\"cus5\":\"\",\"code4\":\"\",\"code2\":\"\"},{\"cus10\":\"\",\"code5\":\"\",\"cus1\":\"\",\"cus4\":\"\",\"cus8\":\"\",\"cus7\":\"\",\"data\":\"\\u003caudio controls autoplay\\u003e \\u003csource src\\u003d\\\"https://bcan.kro.kr/webapp/bgmlist/SilentPartnerSummerSmile.mp3\\\" type\\u003d\\\"audio/mpeg\\\"\\u003eYour browser does not support the audio element.\\u003c/audio\\u003e\",\"cus2\":\"\",\"cus9\":\"\",\"code\":\"\\u003caudio controls autoplay\\u003e \\u003csource src\\u003d\\\"https://bcan.kro.kr/webapp/bgmlist/SilentPartnerSummerSmile.mp3\\\" type\\u003d\\\"audio/mpeg\\\"\\u003eYour browser does not support the audio element.\\u003c/audio\\u003e\",\"cus6\":\"\",\"cusdata\":\"\",\"cus3\":\"\",\"code3\":\"\",\"cus5\":\"\",\"num\":\"0\",\"code4\":\"\",\"cusnum\":\"\",\"code2\":\"\"},{\"cus10\":\"\",\"code5\":\"\",\"cus1\":\"\",\"cus4\":\"\",\"cus7\":\"\",\"cus8\":\"\",\"data\":\"\\u003ch3\\u003eTopherMohrandAlexElena - MrPink\\u003c/h3\\u003e\",\"cus2\":\"\",\"cus9\":\"\",\"code\":\"\\u003ch3\\u003eTopherMohrandAlexElena - MrPink\\u003c/h3\\u003e\",\"cusdata\":\"\",\"cus3\":\"\",\"cus6\":\"\",\"code3\":\"\",\"num\":\"0\",\"cus5\":\"\",\"code4\":\"\",\"cusnum\":\"\",\"code2\":\"\"},{\"cus10\":\"\",\"code5\":\"\",\"cus1\":\"\",\"cus4\":\"\",\"cus7\":\"\",\"cus8\":\"\",\"data\":\"Beep Beep Beeeeeeeeeep Beep Beep Beeeeeeeeeep\",\"cus2\":\"\",\"cus9\":\"\",\"code\":\"\\u003cfont face\\u003d\\\"\\\"\\u003e\\u003cp\\u003eBeep Beep Beeeeeeeeeep Beep Beep Beeeeeeeeeep\\u003c/p\\u003e\",\"cusdata\":\"\",\"cus3\":\"\",\"cus6\":\"\",\"code3\":\"\",\"num\":\"1\",\"cus5\":\"\",\"code4\":\"\",\"code2\":\"\"},{\"cus10\":\"\",\"code5\":\"\",\"cus1\":\"\",\"cus4\":\"\",\"cus7\":\"\",\"cus8\":\"\",\"data\":\"\\u003caudio controls autoplay\\u003e \\u003csource src\\u003d\\\"https://bcan.kro.kr/webapp/bgmlist/TopherMohrandAlexElenaMrPink.mp3\\\" type\\u003d\\\"audio/mpeg\\\"\\u003eYour browser does not support the audio element.\\u003c/audio\\u003e\",\"cus2\":\"\",\"cus9\":\"\",\"code\":\"\\u003caudio controls autoplay\\u003e \\u003csource src\\u003d\\\"https://bcan.kro.kr/webapp/bgmlist/TopherMohrandAlexElenaMrPink.mp3\\\" type\\u003d\\\"audio/mpeg\\\"\\u003eYour browser does not support the audio element.\\u003c/audio\\u003e\",\"cusdata\":\"\",\"cus3\":\"\",\"cus6\":\"\",\"code3\":\"\",\"num\":\"0\",\"cus5\":\"\",\"code4\":\"\",\"cusnum\":\"\",\"code2\":\"\"},{\"cus10\":\"\",\"code5\":\"\",\"cus1\":\"\",\"cus4\":\"\",\"cus8\":\"\",\"cus7\":\"\",\"data\":\"\\u003ch3\\u003eJasonFarnham - Payday\\u003c/h3\\u003e\",\"cus2\":\"\",\"cus9\":\"\",\"code\":\"\\u003ch3\\u003eJasonFarnham - Payday\\u003c/h3\\u003e\",\"cus3\":\"\",\"cus6\":\"\",\"cusdata\":\"\",\"code3\":\"\",\"cus5\":\"\",\"num\":\"0\",\"code4\":\"\",\"cusnum\":\"\",\"code2\":\"\"},{\"cus10\":\"\",\"code5\":\"\",\"cus1\":\"\",\"cus4\":\"\",\"cus8\":\"\",\"cus7\":\"\",\"data\":\":D\",\"cus2\":\"\",\"cus9\":\"\",\"code\":\"\\u003cfont face\\u003d\\\"\\\"\\u003e\\u003cp\\u003e:D\\u003c/p\\u003e\",\"cus3\":\"\",\"cus6\":\"\",\"cusdata\":\"\",\"code3\":\"\",\"cus5\":\"\",\"num\":\"1\",\"code4\":\"\",\"code2\":\"\"},{\"cus10\":\"\",\"code5\":\"\",\"cus1\":\"\",\"cus4\":\"\",\"cus8\":\"\",\"cus7\":\"\",\"data\":\"\\u003caudio controls autoplay\\u003e \\u003csource src\\u003d\\\"https://bcan.kro.kr/webapp/bgmlist/JasonFarnhamPayday.mp3\\\" type\\u003d\\\"audio/mpeg\\\"\\u003eYour browser does not support the audio element.\\u003c/audio\\u003e\",\"cus2\":\"\",\"cus9\":\"\",\"code\":\"\\u003caudio controls autoplay\\u003e \\u003csource src\\u003d\\\"https://bcan.kro.kr/webapp/bgmlist/JasonFarnhamPayday.mp3\\\" type\\u003d\\\"audio/mpeg\\\"\\u003eYour browser does not support the audio element.\\u003c/audio\\u003e\",\"cus3\":\"\",\"cus6\":\"\",\"cusdata\":\"\",\"code3\":\"\",\"cus5\":\"\",\"num\":\"0\",\"code4\":\"\",\"cusnum\":\"\",\"code2\":\"\"},{\"cus10\":\"\",\"code5\":\"\",\"cus1\":\"\",\"cus4\":\"\",\"cus8\":\"\",\"cus7\":\"\",\"data\":\"\\u003ch3\\u003eSilentPartner - SpringInMyStep\\u003c/h3\\u003e\",\"cus2\":\"\",\"cus9\":\"\",\"code\":\"\\u003ch3\\u003eSilentPartner - SpringInMyStep\\u003c/h3\\u003e\",\"cusdata\":\"\",\"cus3\":\"\",\"cus6\":\"\",\"code3\":\"\",\"cus5\":\"\",\"num\":\"0\",\"code4\":\"\",\"cusnum\":\"\",\"code2\":\"\"},{\"cus10\":\"\",\"code5\":\"\",\"cus1\":\"\",\"cus4\":\"\",\"cus8\":\"\",\"cus7\":\"\",\"data\":\"You can download these music\",\"cus2\":\"\",\"cus9\":\"\",\"code\":\"\\u003cfont face\\u003d\\\"\\\"\\u003e\\u003cp\\u003eYou can download these music\\u003c/p\\u003e\",\"cusdata\":\"\",\"cus3\":\"\",\"cus6\":\"\",\"code3\":\"\",\"cus5\":\"\",\"num\":\"1\",\"code4\":\"\",\"code2\":\"\"},{\"cus10\":\"\",\"code5\":\"\",\"cus1\":\"\",\"cus4\":\"\",\"cus8\":\"\",\"cus7\":\"\",\"data\":\"\\u003caudio controls autoplay\\u003e \\u003csource src\\u003d\\\"https://bcan.kro.kr/webapp/bgmlist/SilentPartnerSpringInMyStep.mp3\\\" type\\u003d\\\"audio/mpeg\\\"\\u003eYour browser does not support the audio element.\\u003c/audio\\u003e\",\"cus2\":\"\",\"cus9\":\"\",\"code\":\"\\u003caudio controls autoplay\\u003e \\u003csource src\\u003d\\\"https://bcan.kro.kr/webapp/bgmlist/SilentPartnerSpringInMyStep.mp3\\\" type\\u003d\\\"audio/mpeg\\\"\\u003eYour browser does not support the audio element.\\u003c/audio\\u003e\",\"cusdata\":\"\",\"cus3\":\"\",\"cus6\":\"\",\"code3\":\"\",\"cus5\":\"\",\"num\":\"0\",\"code4\":\"\",\"cusnum\":\"\",\"code2\":\"\"},{\"cus10\":\"\",\"code5\":\"\",\"cus1\":\"\",\"cus4\":\"\",\"cus7\":\"\",\"cus8\":\"\",\"data\":\"\\u003ch3\\u003eSilentPartner - Greenery\\u003c/h3\\u003e\",\"cus2\":\"\",\"cus9\":\"\",\"code\":\"\\u003ch3\\u003eSilentPartner - Greenery\\u003c/h3\\u003e\",\"cus3\":\"\",\"cus6\":\"\",\"cusdata\":\"\",\"code3\":\"\",\"num\":\"0\",\"cus5\":\"\",\"code4\":\"\",\"cusnum\":\"\",\"code2\":\"\"},{\"cus10\":\"\",\"code5\":\"\",\"cus1\":\"\",\"cus4\":\"\",\"cus7\":\"\",\"cus8\":\"\",\"data\":\"Do you know this?\",\"cus2\":\"\",\"cus9\":\"\",\"code\":\"\\u003cfont face\\u003d\\\"\\\"\\u003e\\u003cp\\u003eDo you know this?\\u003c/p\\u003e\",\"cus3\":\"\",\"cus6\":\"\",\"cusdata\":\"\",\"code3\":\"\",\"num\":\"1\",\"cus5\":\"\",\"code4\":\"\",\"code2\":\"\"},{\"cus10\":\"\",\"code5\":\"\",\"cus1\":\"\",\"cus4\":\"\",\"cus7\":\"\",\"cus8\":\"\",\"data\":\"\\u003caudio controls autoplay\\u003e \\u003csource src\\u003d\\\"https://bcan.kro.kr/webapp/bgmlist/SilentPartnerGreenery.mp3\\\" type\\u003d\\\"audio/mpeg\\\"\\u003eYour browser does not support the audio element.\\u003c/audio\\u003e\",\"cus2\":\"\",\"cus9\":\"\",\"code\":\"\\u003caudio controls autoplay\\u003e \\u003csource src\\u003d\\\"https://bcan.kro.kr/webapp/bgmlist/SilentPartnerGreenery.mp3\\\" type\\u003d\\\"audio/mpeg\\\"\\u003eYour browser does not support the audio element.\\u003c/audio\\u003e\",\"cus3\":\"\",\"cus6\":\"\",\"cusdata\":\"\",\"code3\":\"\",\"num\":\"0\",\"cus5\":\"\",\"code4\":\"\",\"cusnum\":\"\",\"code2\":\"\"},{\"cus10\":\"\",\"code5\":\"\",\"cus1\":\"\",\"cus4\":\"\",\"cus7\":\"\",\"cus8\":\"\",\"data\":\"\\u003ch3\\u003eVibeTracks - AboutThatOldie\\u003c/h3\\u003e\",\"cus2\":\"\",\"cus9\":\"\",\"code\":\"\\u003ch3\\u003eVibeTracks - AboutThatOldie\\u003c/h3\\u003e\",\"cus3\":\"\",\"cus6\":\"\",\"cusdata\":\"\",\"code3\":\"\",\"num\":\"0\",\"cus5\":\"\",\"code4\":\"\",\"cusnum\":\"\",\"code2\":\"\"},{\"cus10\":\"\",\"code5\":\"\",\"cus1\":\"\",\"cus4\":\"\",\"cus7\":\"\",\"cus8\":\"\",\"data\":\"DDDODDDODDDDDDDODDDODDDODDDDDDDO\",\"cus2\":\"\",\"cus9\":\"\",\"code\":\"\\u003cfont face\\u003d\\\"\\\"\\u003e\\u003cp\\u003eDDDODDDODDDDDDDODDDODDDODDDDDDDO\\u003c/p\\u003e\",\"cus3\":\"\",\"cus6\":\"\",\"cusdata\":\"\",\"code3\":\"\",\"num\":\"1\",\"cus5\":\"\",\"code4\":\"\",\"code2\":\"\"},{\"cus10\":\"\",\"code5\":\"\",\"cus1\":\"\",\"cus4\":\"\",\"cus7\":\"\",\"cus8\":\"\",\"data\":\"\\u003caudio controls autoplay\\u003e \\u003csource src\\u003d\\\"https://bcan.kro.kr/webapp/bgmlist/VibeTracksAboutThatOldie.mp3\\\" type\\u003d\\\"audio/mpeg\\\"\\u003eYour browser does not support the audio element.\\u003c/audio\\u003e\",\"cus2\":\"\",\"cus9\":\"\",\"code\":\"\\u003caudio controls autoplay\\u003e \\u003csource src\\u003d\\\"https://bcan.kro.kr/webapp/bgmlist/VibeTracksAboutThatOldie.mp3\\\" type\\u003d\\\"audio/mpeg\\\"\\u003eYour browser does not support the audio element.\\u003c/audio\\u003e\",\"cus3\":\"\",\"cus6\":\"\",\"cusdata\":\"\",\"code3\":\"\",\"num\":\"0\",\"cus5\":\"\",\"code4\":\"\",\"cusnum\":\"\",\"code2\":\"\"},{\"cus10\":\"\",\"code5\":\"\",\"cus1\":\"\",\"cus4\":\"\",\"cus8\":\"\",\"cus7\":\"\",\"data\":\"Version 1.0 Release | by Blackcats4567\",\"cus2\":\"\",\"cus9\":\"\",\"code\":\"\\u003cfont face\\u003d\\\"\\\"\\u003e\\u003cp\\u003e \\u003ca href \\u003d \\\"https://clickhtml.kro.kr\\\" target \\u003d \\\"_self\\\"\\u003eVersion 1.0 Release | by Blackcats4567\\u003c/a\\u003e \\u003c/h1\\u003e\",\"cus6\":\"\",\"cusdata\":\"\",\"cus3\":\"\",\"code3\":\"https://clickhtml.kro.kr\",\"cus5\":\"\",\"num\":\"1\",\"code4\":\"\",\"code2\":\"\"},{\"cus10\":\"\",\"code5\":\"\",\"cus1\":\"\",\"cus4\":\"\",\"cus8\":\"\",\"cus7\":\"\",\"data\":\"\",\"cus2\":\"\",\"cus9\":\"\",\"code\":\"\\u003c/body\\u003e\",\"cus6\":\"\",\"cusdata\":\"\",\"cus3\":\"\",\"code3\":\"\",\"cus5\":\"\",\"num\":\"5\",\"code4\":\"\",\"cusnum\":\"\",\"code2\":\"\"}]",
        "rank" : "OWNER",
        "time" : "04/21/2020 09:00:09 AM",
        "title" : "Youtube BGM list (1.0)",
        "type" : "1",
        "uploader" : "lee25802733@gmail.com"
}
{
        "appver" : "2",
        "des" : "[Update LOG]\n(0.1 Beta)\n*Release\n(1.0 Production)\n*Added 3 BGM\n*Deleted Korean version\n(1.1 Production)\n*Added icon",
        "dev" : "Blackcats4567",
        "file" : "[{\"code4\":\"\",\"code3\":\"\",\"code2\":\"\",\"code\":\"\\u003chead\\u003e\",\"data\":\"\",\"num\":\"2\",\"cus10\":\"\",\"code5\":\"\",\"cusnum\":\"\",\"cus9\":\"\",\"cus7\":\"\",\"cusdata\":\"\",\"cus8\":\"\",\"cus5\":\"\",\"cus6\":\"\",\"cus3\":\"\",\"cus4\":\"\",\"cus1\":\"\",\"cus2\":\"\"},{\"code4\":\"\",\"code3\":\"\",\"code2\":\"\",\"code\":\"\\u003ctitle\\u003eYOUTUBE BGM LIST\\u003c/title\\u003e\",\"data\":\"YOUTUBE BGM LIST\",\"num\":\"13\",\"cus10\":\"\",\"code5\":\"\",\"cusnum\":\"\",\"cus9\":\"\",\"cus7\":\"\",\"cusdata\":\"\",\"cus8\":\"\",\"cus5\":\"\",\"cus6\":\"\",\"cus3\":\"\",\"cus4\":\"\",\"cus1\":\"\",\"cus2\":\"\"},{\"code4\":\"\",\"code3\":\"\",\"code2\":\"\",\"code\":\"\\u003clink rel\\u003d\\\"shortcut icon\\\" href\\u003d\\\"https://bcan.kro.kr/files/bcan.png\\\" type\\u003d\\\"image/png\\\"\\u003e\",\"data\":\"https://bcan.kro.kr/files/bcan.png\",\"num\":\"14\",\"cus10\":\"\",\"code5\":\"\",\"cusnum\":\"\",\"cus9\":\"\",\"cus7\":\"\",\"cusdata\":\"\",\"cus8\":\"\",\"cus5\":\"\",\"cus6\":\"\",\"cus3\":\"\",\"cus4\":\"\",\"cus1\":\"\",\"cus2\":\"\"},{\"code4\":\"\",\"code3\":\"\",\"code2\":\"\",\"code\":\"\\u003c/head\\u003e\",\"data\":\"\",\"num\":\"3\",\"cus10\":\"\",\"code5\":\"\",\"cusnum\":\"\",\"cus9\":\"\",\"cus7\":\"\",\"cusdata\":\"\",\"cus8\":\"\",\"cus5\":\"\",\"cus6\":\"\",\"cus3\":\"\",\"cus4\":\"\",\"cus1\":\"\",\"cus2\":\"\"},{\"code4\":\"\",\"code3\":\"\",\"code2\":\"\",\"code\":\"\\u003cbody\\u003e\",\"data\":\"\",\"num\":\"4\",\"cus10\":\"\",\"code5\":\"\",\"cusnum\":\"\",\"cus9\":\"\",\"cus7\":\"\",\"cusdata\":\"\",\"cus8\":\"\",\"cus5\":\"\",\"cus6\":\"\",\"cus3\":\"\",\"cus4\":\"\",\"cus1\":\"\",\"cus2\":\"\"},{\"code4\":\"\",\"code3\":\"\",\"code2\":\"\",\"code\":\"\\u003ch1\\u003eBGM LIST\\u003c/h1\\u003e\\u003ch3\\u003eTheFatRat - TimeLapse\\u003c/h3\\u003e\",\"data\":\"\\u003ch1\\u003eBGM LIST\\u003c/h1\\u003e\\u003ch3\\u003eTheFatRat - TimeLapse\\u003c/h3\\u003e\",\"num\":\"0\",\"cus10\":\"\",\"code5\":\"\",\"cusnum\":\"\",\"cus9\":\"\",\"cus7\":\"\",\"cusdata\":\"\",\"cus8\":\"\",\"cus5\":\"\",\"cus6\":\"\",\"cus3\":\"\",\"cus4\":\"\",\"cus1\":\"\",\"cus2\":\"\"},{\"code4\":\"\",\"code3\":\"\",\"code2\":\"\",\"code\":\"\\u003cfont face\\u003d\\\"\\\"\\u003e\\u003cp\\u003eGood bgm\\u003c/p\\u003e\",\"data\":\"Good bgm\",\"num\":\"1\",\"cus10\":\"\",\"code5\":\"\",\"cus9\":\"\",\"cus7\":\"\",\"cusdata\":\"\",\"cus8\":\"\",\"cus5\":\"\",\"cus6\":\"\",\"cus3\":\"\",\"cus4\":\"\",\"cus1\":\"\",\"cus2\":\"\"},{\"code4\":\"\",\"code3\":\"\",\"code2\":\"\",\"code\":\"\\u003caudio controls autoplay\\u003e \\u003csource src\\u003d\\\"https://bcan.kro.kr/webapp/bgmlist/TheFatRatTimeLapse.mp3\\\" type\\u003d\\\"audio/mpeg\\\"\\u003eYour browser does not support the audio element.\\u003c/audio\\u003e\",\"data\":\"\\u003caudio controls autoplay\\u003e \\u003csource src\\u003d\\\"https://bcan.kro.kr/webapp/bgmlist/TheFatRatTimeLapse.mp3\\\" type\\u003d\\\"audio/mpeg\\\"\\u003eYour browser does not support the audio element.\\u003c/audio\\u003e\",\"num\":\"0\",\"cus10\":\"\",\"code5\":\"\",\"cusnum\":\"\",\"cus9\":\"\",\"cus7\":\"\",\"cusdata\":\"\",\"cus8\":\"\",\"cus5\":\"\",\"cus6\":\"\",\"cus3\":\"\",\"cus4\":\"\",\"cus1\":\"\",\"cus2\":\"\"},{\"code4\":\"\",\"code3\":\"\",\"code2\":\"\",\"code\":\"\\u003ch3\\u003eTheFatRat - Unity\\u003c/h3\\u003e\",\"data\":\"\\u003ch3\\u003eTheFatRat - Unity\\u003c/h3\\u003e\",\"num\":\"0\",\"cus10\":\"\",\"code5\":\"\",\"cusnum\":\"\",\"cus9\":\"\",\"cus7\":\"\",\"cusdata\":\"\",\"cus8\":\"\",\"cus5\":\"\",\"cus6\":\"\",\"cus3\":\"\",\"cus4\":\"\",\"cus1\":\"\",\"cus2\":\"\"},{\"code4\":\"\",\"code3\":\"\",\"code2\":\"\",\"code\":\"\\u003cfont face\\u003d\\\"\\\"\\u003e\\u003cp\\u003eXD\\u003c/p\\u003e\",\"data\":\"XD\",\"num\":\"1\",\"cus10\":\"\",\"code5\":\"\",\"cus9\":\"\",\"cus7\":\"\",\"cusdata\":\"\",\"cus8\":\"\",\"cus5\":\"\",\"cus6\":\"\",\"cus3\":\"\",\"cus4\":\"\",\"cus1\":\"\",\"cus2\":\"\"},{\"code4\":\"\",\"code3\":\"\",\"code2\":\"\",\"code\":\"\\u003caudio controls autoplay\\u003e \\u003csource src\\u003d\\\"https://bcan.kro.kr/webapp/bgmlist/TheFatRatUnity.mp3\\\" type\\u003d\\\"audio/mpeg\\\"\\u003eYour browser does not support the audio element.\\u003c/audio\\u003e\",\"data\":\"\\u003caudio controls autoplay\\u003e \\u003csource src\\u003d\\\"https://bcan.kro.kr/webapp/bgmlist/TheFatRatUnity.mp3\\\" type\\u003d\\\"audio/mpeg\\\"\\u003eYour browser does not support the audio element.\\u003c/audio\\u003e\",\"num\":\"0\",\"cus10\":\"\",\"code5\":\"\",\"cusnum\":\"\",\"cus9\":\"\",\"cus7\":\"\",\"cusdata\":\"\",\"cus8\":\"\",\"cus5\":\"\",\"cus6\":\"\",\"cus3\":\"\",\"cus4\":\"\",\"cus1\":\"\",\"cus2\":\"\"},{\"code4\":\"\",\"code3\":\"\",\"code2\":\"\",\"code\":\"\\u003ch3\\u003eAlan Walker - Fade\\u003c/h3\\u003e\",\"data\":\"\\u003ch3\\u003eAlan Walker - Fade\\u003c/h3\\u003e\",\"num\":\"0\",\"cus10\":\"\",\"code5\":\"\",\"cusnum\":\"\",\"cus9\":\"\",\"cus7\":\"\",\"cusdata\":\"\",\"cus8\":\"\",\"cus5\":\"\",\"cus6\":\"\",\"cus3\":\"\",\"cus4\":\"\",\"cus1\":\"\",\"cus2\":\"\"},{\"code4\":\"\",\"code3\":\"\",\"code2\":\"\",\"code\":\"\\u003cfont face\\u003d\\\"\\\"\\u003e\\u003cp\\u003eFamous song\\u003c/p\\u003e\",\"data\":\"Famous song\",\"num\":\"1\",\"cus10\":\"\",\"code5\":\"\",\"cus9\":\"\",\"cus7\":\"\",\"cusdata\":\"\",\"cus8\":\"\",\"cus5\":\"\",\"cus6\":\"\",\"cus3\":\"\",\"cus4\":\"\",\"cus1\":\"\",\"cus2\":\"\"},{\"code4\":\"\",\"code3\":\"\",\"code2\":\"\",\"code\":\"\\u003caudio controls autoplay\\u003e \\u003csource src\\u003d\\\"https://bcan.kro.kr/webapp/bgmlist/AlanWalkerFade.mp3\\\" type\\u003d\\\"audio/mpeg\\\"\\u003eYour browser does not support the audio element.\\u003c/audio\\u003e\",\"data\":\"\\u003caudio controls autoplay\\u003e \\u003csource src\\u003d\\\"https://bcan.kro.kr/webapp/bgmlist/AlanWalkerFade.mp3\\\" type\\u003d\\\"audio/mpeg\\\"\\u003eYour browser does not support the audio element.\\u003c/audio\\u003e\",\"num\":\"0\",\"cus10\":\"\",\"code5\":\"\",\"cusnum\":\"\",\"cus9\":\"\",\"cus7\":\"\",\"cusdata\":\"\",\"cus8\":\"\",\"cus5\":\"\",\"cus6\":\"\",\"cus3\":\"\",\"cus4\":\"\",\"cus1\":\"\",\"cus2\":\"\"},{\"code4\":\"\",\"code3\":\"\",\"code2\":\"\",\"code\":\"\\u003ch3\\u003eVexento - We Are One\\u003c/h3\\u003e\",\"data\":\"\\u003ch3\\u003eVexento - We Are One\\u003c/h3\\u003e\",\"num\":\"0\",\"cus10\":\"\",\"code5\":\"\",\"cusnum\":\"\",\"cus9\":\"\",\"cus7\":\"\",\"cusdata\":\"\",\"cus8\":\"\",\"cus5\":\"\",\"cus6\":\"\",\"cus3\":\"\",\"cus4\":\"\",\"cus1\":\"\",\"cus2\":\"\"},{\"code4\":\"\",\"code3\":\"\",\"code2\":\"\",\"code\":\"\\u003cfont face\\u003d\\\"\\\"\\u003e\\u003cp\\u003eGG!\\u003c/p\\u003e\",\"data\":\"GG!\",\"num\":\"1\",\"cus10\":\"\",\"code5\":\"\",\"cus9\":\"\",\"cus7\":\"\",\"cusdata\":\"\",\"cus8\":\"\",\"cus5\":\"\",\"cus6\":\"\",\"cus3\":\"\",\"cus4\":\"\",\"cus1\":\"\",\"cus2\":\"\"},{\"code4\":\"\",\"code3\":\"\",\"code2\":\"\",\"code\":\"\\u003caudio controls autoplay\\u003e \\u003csource src\\u003d\\\"https://bcan.kro.kr/webapp/bgmlist/WeAreOneVexento.mp3\\\" type\\u003d\\\"audio/mpeg\\\"\\u003eYour browser does not support the audio element.\\u003c/audio\\u003e\",\"data\":\"\\u003caudio controls autoplay\\u003e \\u003csource src\\u003d\\\"https://bcan.kro.kr/webapp/bgmlist/WeAreOneVexento.mp3\\\" type\\u003d\\\"audio/mpeg\\\"\\u003eYour browser does not support the audio element.\\u003c/audio\\u003e\",\"num\":\"0\",\"cus10\":\"\",\"code5\":\"\",\"cusnum\":\"\",\"cus9\":\"\",\"cus7\":\"\",\"cusdata\":\"\",\"cus8\":\"\",\"cus5\":\"\",\"cus6\":\"\",\"cus3\":\"\",\"cus4\":\"\",\"cus1\":\"\",\"cus2\":\"\"},{\"code4\":\"\",\"code3\":\"\",\"code2\":\"\",\"code\":\"\\u003ch3\\u003eSilentPartner - BlueSkies\\u003c/h3\\u003e\",\"data\":\"\\u003ch3\\u003eSilentPartner - BlueSkies\\u003c/h3\\u003e\",\"num\":\"0\",\"cus10\":\"\",\"code5\":\"\",\"cusnum\":\"\",\"cus9\":\"\",\"cus7\":\"\",\"cusdata\":\"\",\"cus8\":\"\",\"cus5\":\"\",\"cus6\":\"\",\"cus3\":\"\",\"cus4\":\"\",\"cus1\":\"\",\"cus2\":\"\"},{\"code4\":\"\",\"code3\":\"\",\"code2\":\"\",\"code\":\"\\u003cfont face\\u003d\\\"\\\"\\u003e\\u003cp\\u003eWhere have you not heard?\\u003c/p\\u003e\",\"data\":\"Where have you not heard?\",\"num\":\"1\",\"cus10\":\"\",\"code5\":\"\",\"cus9\":\"\",\"cus7\":\"\",\"cusdata\":\"\",\"cus8\":\"\",\"cus5\":\"\",\"cus6\":\"\",\"cus3\":\"\",\"cus4\":\"\",\"cus1\":\"\",\"cus2\":\"\"},{\"code4\":\"\",\"code3\":\"\",\"code2\":\"\",\"code\":\"\\u003caudio controls autoplay\\u003e \\u003csource src\\u003d\\\"https://bcan.kro.kr/webapp/bgmlist/SilentPartnerBlueSkies.mp3\\\" type\\u003d\\\"audio/mpeg\\\"\\u003eYour browser does not support the audio element.\\u003c/audio\\u003e\",\"data\":\"\\u003caudio controls autoplay\\u003e \\u003csource src\\u003d\\\"https://bcan.kro.kr/webapp/bgmlist/SilentPartnerBlueSkies.mp3\\\" type\\u003d\\\"audio/mpeg\\\"\\u003eYour browser does not support the audio element.\\u003c/audio\\u003e\",\"num\":\"0\",\"cus10\":\"\",\"code5\":\"\",\"cusnum\":\"\",\"cus9\":\"\",\"cus7\":\"\",\"cusdata\":\"\",\"cus8\":\"\",\"cus5\":\"\",\"cus6\":\"\",\"cus3\":\"\",\"cus4\":\"\",\"cus1\":\"\",\"cus2\":\"\"},{\"code4\":\"\",\"code3\":\"\",\"code2\":\"\",\"code\":\"\\u003ch3\\u003eSilentPartner - SugarZone\\u003c/h3\\u003e\",\"data\":\"\\u003ch3\\u003eSilentPartner - SugarZone\\u003c/h3\\u003e\",\"num\":\"0\",\"cus10\":\"\",\"code5\":\"\",\"cusnum\":\"\",\"cus9\":\"\",\"cus7\":\"\",\"cusdata\":\"\",\"cus8\":\"\",\"cus5\":\"\",\"cus6\":\"\",\"cus3\":\"\",\"cus4\":\"\",\"cus1\":\"\",\"cus2\":\"\"},{\"code4\":\"\",\"code3\":\"\",\"code2\":\"\",\"code\":\"\\u003cfont face\\u003d\\\"\\\"\\u003e\\u003cp\\u003eI know this background music!\\u003c/p\\u003e\",\"data\":\"I know this background music!\",\"num\":\"1\",\"cus10\":\"\",\"code5\":\"\",\"cus9\":\"\",\"cus7\":\"\",\"cusdata\":\"\",\"cus8\":\"\",\"cus5\":\"\",\"cus6\":\"\",\"cus3\":\"\",\"cus4\":\"\",\"cus1\":\"\",\"cus2\":\"\"},{\"code4\":\"\",\"code3\":\"\",\"code2\":\"\",\"code\":\"\\u003caudio controls autoplay\\u003e \\u003csource src\\u003d\\\"https://bcan.kro.kr/webapp/bgmlist/SilentPartnerSugarZone.mp3\\\" type\\u003d\\\"audio/mpeg\\\"\\u003eYour browser does not support the audio element.\\u003c/audio\\u003e\",\"data\":\"\\u003caudio controls autoplay\\u003e \\u003csource src\\u003d\\\"https://bcan.kro.kr/webapp/bgmlist/SilentPartnerSugarZone.mp3\\\" type\\u003d\\\"audio/mpeg\\\"\\u003eYour browser does not support the audio element.\\u003c/audio\\u003e\",\"num\":\"0\",\"cus10\":\"\",\"code5\":\"\",\"cusnum\":\"\",\"cus9\":\"\",\"cus7\":\"\",\"cusdata\":\"\",\"cus8\":\"\",\"cus5\":\"\",\"cus6\":\"\",\"cus3\":\"\",\"cus4\":\"\",\"cus1\":\"\",\"cus2\":\"\"},{\"code4\":\"\",\"code3\":\"\",\"code2\":\"\",\"code\":\"\\u003ch3\\u003eSilentPartner - SummerSmile\\u003c/h3\\u003e\",\"data\":\"\\u003ch3\\u003eSilentPartner - SummerSmile\\u003c/h3\\u003e\",\"num\":\"0\",\"cus10\":\"\",\"code5\":\"\",\"cusnum\":\"\",\"cus9\":\"\",\"cus7\":\"\",\"cusdata\":\"\",\"cus8\":\"\",\"cus5\":\"\",\"cus6\":\"\",\"cus3\":\"\",\"cus4\":\"\",\"cus1\":\"\",\"cus2\":\"\"},{\"code4\":\"\",\"code3\":\"\",\"code2\":\"\",\"code\":\"\\u003cfont face\\u003d\\\"\\\"\\u003e\\u003cp\\u003eSilent Partner 👍\\u003c/p\\u003e\",\"data\":\"Silent Partner 👍\",\"num\":\"1\",\"cus10\":\"\",\"code5\":\"\",\"cus9\":\"\",\"cus7\":\"\",\"cusdata\":\"\",\"cus8\":\"\",\"cus5\":\"\",\"cus6\":\"\",\"cus3\":\"\",\"cus4\":\"\",\"cus1\":\"\",\"cus2\":\"\"},{\"code4\":\"\",\"code3\":\"\",\"code2\":\"\",\"code\":\"\\u003caudio controls autoplay\\u003e \\u003csource src\\u003d\\\"https://bcan.kro.kr/webapp/bgmlist/SilentPartnerSummerSmile.mp3\\\" type\\u003d\\\"audio/mpeg\\\"\\u003eYour browser does not support the audio element.\\u003c/audio\\u003e\",\"data\":\"\\u003caudio controls autoplay\\u003e \\u003csource src\\u003d\\\"https://bcan.kro.kr/webapp/bgmlist/SilentPartnerSummerSmile.mp3\\\" type\\u003d\\\"audio/mpeg\\\"\\u003eYour browser does not support the audio element.\\u003c/audio\\u003e\",\"num\":\"0\",\"cus10\":\"\",\"code5\":\"\",\"cusnum\":\"\",\"cus9\":\"\",\"cus7\":\"\",\"cusdata\":\"\",\"cus8\":\"\",\"cus5\":\"\",\"cus6\":\"\",\"cus3\":\"\",\"cus4\":\"\",\"cus1\":\"\",\"cus2\":\"\"},{\"code4\":\"\",\"code3\":\"\",\"code2\":\"\",\"code\":\"\\u003ch3\\u003eTopherMohrandAlexElena - MrPink\\u003c/h3\\u003e\",\"data\":\"\\u003ch3\\u003eTopherMohrandAlexElena - MrPink\\u003c/h3\\u003e\",\"num\":\"0\",\"cus10\":\"\",\"code5\":\"\",\"cusnum\":\"\",\"cus9\":\"\",\"cus7\":\"\",\"cusdata\":\"\",\"cus8\":\"\",\"cus5\":\"\",\"cus6\":\"\",\"cus3\":\"\",\"cus4\":\"\",\"cus1\":\"\",\"cus2\":\"\"},{\"code4\":\"\",\"code3\":\"\",\"code2\":\"\",\"code\":\"\\u003cfont face\\u003d\\\"\\\"\\u003e\\u003cp\\u003eBeep Beep Beeeeeeeeeep Beep Beep Beeeeeeeeeep\\u003c/p\\u003e\",\"data\":\"Beep Beep Beeeeeeeeeep Beep Beep Beeeeeeeeeep\",\"num\":\"1\",\"cus10\":\"\",\"code5\":\"\",\"cus9\":\"\",\"cus7\":\"\",\"cusdata\":\"\",\"cus8\":\"\",\"cus5\":\"\",\"cus6\":\"\",\"cus3\":\"\",\"cus4\":\"\",\"cus1\":\"\",\"cus2\":\"\"},{\"code4\":\"\",\"code3\":\"\",\"code2\":\"\",\"code\":\"\\u003caudio controls autoplay\\u003e \\u003csource src\\u003d\\\"https://bcan.kro.kr/webapp/bgmlist/TopherMohrandAlexElenaMrPink.mp3\\\" type\\u003d\\\"audio/mpeg\\\"\\u003eYour browser does not support the audio element.\\u003c/audio\\u003e\",\"data\":\"\\u003caudio controls autoplay\\u003e \\u003csource src\\u003d\\\"https://bcan.kro.kr/webapp/bgmlist/TopherMohrandAlexElenaMrPink.mp3\\\" type\\u003d\\\"audio/mpeg\\\"\\u003eYour browser does not support the audio element.\\u003c/audio\\u003e\",\"num\":\"0\",\"cus10\":\"\",\"code5\":\"\",\"cusnum\":\"\",\"cus9\":\"\",\"cus7\":\"\",\"cusdata\":\"\",\"cus8\":\"\",\"cus5\":\"\",\"cus6\":\"\",\"cus3\":\"\",\"cus4\":\"\",\"cus1\":\"\",\"cus2\":\"\"},{\"code4\":\"\",\"code3\":\"\",\"code2\":\"\",\"code\":\"\\u003ch3\\u003eJasonFarnham - Payday\\u003c/h3\\u003e\",\"data\":\"\\u003ch3\\u003eJasonFarnham - Payday\\u003c/h3\\u003e\",\"num\":\"0\",\"cus10\":\"\",\"code5\":\"\",\"cusnum\":\"\",\"cus9\":\"\",\"cus7\":\"\",\"cusdata\":\"\",\"cus8\":\"\",\"cus5\":\"\",\"cus6\":\"\",\"cus3\":\"\",\"cus4\":\"\",\"cus1\":\"\",\"cus2\":\"\"},{\"code4\":\"\",\"code3\":\"\",\"code2\":\"\",\"code\":\"\\u003cfont face\\u003d\\\"\\\"\\u003e\\u003cp\\u003e:D\\u003c/p\\u003e\",\"data\":\":D\",\"num\":\"1\",\"cus10\":\"\",\"code5\":\"\",\"cus9\":\"\",\"cus7\":\"\",\"cusdata\":\"\",\"cus8\":\"\",\"cus5\":\"\",\"cus6\":\"\",\"cus3\":\"\",\"cus4\":\"\",\"cus1\":\"\",\"cus2\":\"\"},{\"code4\":\"\",\"code3\":\"\",\"code2\":\"\",\"code\":\"\\u003caudio controls autoplay\\u003e \\u003csource src\\u003d\\\"https://bcan.kro.kr/webapp/bgmlist/JasonFarnhamPayday.mp3\\\" type\\u003d\\\"audio/mpeg\\\"\\u003eYour browser does not support the audio element.\\u003c/audio\\u003e\",\"data\":\"\\u003caudio controls autoplay\\u003e \\u003csource src\\u003d\\\"https://bcan.kro.kr/webapp/bgmlist/JasonFarnhamPayday.mp3\\\" type\\u003d\\\"audio/mpeg\\\"\\u003eYour browser does not support the audio element.\\u003c/audio\\u003e\",\"num\":\"0\",\"cus10\":\"\",\"code5\":\"\",\"cusnum\":\"\",\"cus9\":\"\",\"cus7\":\"\",\"cusdata\":\"\",\"cus8\":\"\",\"cus5\":\"\",\"cus6\":\"\",\"cus3\":\"\",\"cus4\":\"\",\"cus1\":\"\",\"cus2\":\"\"},{\"code4\":\"\",\"code3\":\"\",\"code2\":\"\",\"code\":\"\\u003ch3\\u003eSilentPartner - SpringInMyStep\\u003c/h3\\u003e\",\"data\":\"\\u003ch3\\u003eSilentPartner - SpringInMyStep\\u003c/h3\\u003e\",\"num\":\"0\",\"cus10\":\"\",\"code5\":\"\",\"cusnum\":\"\",\"cus9\":\"\",\"cus7\":\"\",\"cusdata\":\"\",\"cus8\":\"\",\"cus5\":\"\",\"cus6\":\"\",\"cus3\":\"\",\"cus4\":\"\",\"cus1\":\"\",\"cus2\":\"\"},{\"code4\":\"\",\"code3\":\"\",\"code2\":\"\",\"code\":\"\\u003cfont face\\u003d\\\"\\\"\\u003e\\u003cp\\u003eYou can download these music\\u003c/p\\u003e\",\"data\":\"You can download these music\",\"num\":\"1\",\"cus10\":\"\",\"code5\":\"\",\"cus9\":\"\",\"cus7\":\"\",\"cusdata\":\"\",\"cus8\":\"\",\"cus5\":\"\",\"cus6\":\"\",\"cus3\":\"\",\"cus4\":\"\",\"cus1\":\"\",\"cus2\":\"\"},{\"code4\":\"\",\"code3\":\"\",\"code2\":\"\",\"code\":\"\\u003caudio controls autoplay\\u003e \\u003csource src\\u003d\\\"https://bcan.kro.kr/webapp/bgmlist/SilentPartnerSpringInMyStep.mp3\\\" type\\u003d\\\"audio/mpeg\\\"\\u003eYour browser does not support the audio element.\\u003c/audio\\u003e\",\"data\":\"\\u003caudio controls autoplay\\u003e \\u003csource src\\u003d\\\"https://bcan.kro.kr/webapp/bgmlist/SilentPartnerSpringInMyStep.mp3\\\" type\\u003d\\\"audio/mpeg\\\"\\u003eYour browser does not support the audio element.\\u003c/audio\\u003e\",\"num\":\"0\",\"cus10\":\"\",\"code5\":\"\",\"cusnum\":\"\",\"cus9\":\"\",\"cus7\":\"\",\"cusdata\":\"\",\"cus8\":\"\",\"cus5\":\"\",\"cus6\":\"\",\"cus3\":\"\",\"cus4\":\"\",\"cus1\":\"\",\"cus2\":\"\"},{\"code4\":\"\",\"code3\":\"\",\"code2\":\"\",\"code\":\"\\u003ch3\\u003eSilentPartner - Greenery\\u003c/h3\\u003e\",\"data\":\"\\u003ch3\\u003eSilentPartner - Greenery\\u003c/h3\\u003e\",\"num\":\"0\",\"cus10\":\"\",\"code5\":\"\",\"cusnum\":\"\",\"cus9\":\"\",\"cus7\":\"\",\"cusdata\":\"\",\"cus8\":\"\",\"cus5\":\"\",\"cus6\":\"\",\"cus3\":\"\",\"cus4\":\"\",\"cus1\":\"\",\"cus2\":\"\"},{\"code4\":\"\",\"code3\":\"\",\"code2\":\"\",\"code\":\"\\u003cfont face\\u003d\\\"\\\"\\u003e\\u003cp\\u003eDo you know this?\\u003c/p\\u003e\",\"data\":\"Do you know this?\",\"num\":\"1\",\"cus10\":\"\",\"code5\":\"\",\"cus9\":\"\",\"cus7\":\"\",\"cusdata\":\"\",\"cus8\":\"\",\"cus5\":\"\",\"cus6\":\"\",\"cus3\":\"\",\"cus4\":\"\",\"cus1\":\"\",\"cus2\":\"\"},{\"code4\":\"\",\"code3\":\"\",\"code2\":\"\",\"code\":\"\\u003caudio controls autoplay\\u003e \\u003csource src\\u003d\\\"https://bcan.kro.kr/webapp/bgmlist/SilentPartnerGreenery.mp3\\\" type\\u003d\\\"audio/mpeg\\\"\\u003eYour browser does not support the audio element.\\u003c/audio\\u003e\",\"data\":\"\\u003caudio controls autoplay\\u003e \\u003csource src\\u003d\\\"https://bcan.kro.kr/webapp/bgmlist/SilentPartnerGreenery.mp3\\\" type\\u003d\\\"audio/mpeg\\\"\\u003eYour browser does not support the audio element.\\u003c/audio\\u003e\",\"num\":\"0\",\"cus10\":\"\",\"code5\":\"\",\"cusnum\":\"\",\"cus9\":\"\",\"cus7\":\"\",\"cusdata\":\"\",\"cus8\":\"\",\"cus5\":\"\",\"cus6\":\"\",\"cus3\":\"\",\"cus4\":\"\",\"cus1\":\"\",\"cus2\":\"\"},{\"code4\":\"\",\"code3\":\"\",\"code2\":\"\",\"code\":\"\\u003ch3\\u003eVibeTracks - AboutThatOldie\\u003c/h3\\u003e\",\"data\":\"\\u003ch3\\u003eVibeTracks - AboutThatOldie\\u003c/h3\\u003e\",\"num\":\"0\",\"cus10\":\"\",\"code5\":\"\",\"cusnum\":\"\",\"cus9\":\"\",\"cus7\":\"\",\"cusdata\":\"\",\"cus8\":\"\",\"cus5\":\"\",\"cus6\":\"\",\"cus3\":\"\",\"cus4\":\"\",\"cus1\":\"\",\"cus2\":\"\"},{\"code4\":\"\",\"code3\":\"\",\"code2\":\"\",\"code\":\"\\u003cfont face\\u003d\\\"\\\"\\u003e\\u003cp\\u003eDDDODDDODDDDDDDODDDODDDODDDDDDDO\\u003c/p\\u003e\",\"data\":\"DDDODDDODDDDDDDODDDODDDODDDDDDDO\",\"num\":\"1\",\"cus10\":\"\",\"code5\":\"\",\"cus9\":\"\",\"cus7\":\"\",\"cusdata\":\"\",\"cus8\":\"\",\"cus5\":\"\",\"cus6\":\"\",\"cus3\":\"\",\"cus4\":\"\",\"cus1\":\"\",\"cus2\":\"\"},{\"code4\":\"\",\"code3\":\"\",\"code2\":\"\",\"code\":\"\\u003caudio controls autoplay\\u003e \\u003csource src\\u003d\\\"https://bcan.kro.kr/webapp/bgmlist/VibeTracksAboutThatOldie.mp3\\\" type\\u003d\\\"audio/mpeg\\\"\\u003eYour browser does not support the audio element.\\u003c/audio\\u003e\",\"data\":\"\\u003caudio controls autoplay\\u003e \\u003csource src\\u003d\\\"https://bcan.kro.kr/webapp/bgmlist/VibeTracksAboutThatOldie.mp3\\\" type\\u003d\\\"audio/mpeg\\\"\\u003eYour browser does not support the audio element.\\u003c/audio\\u003e\",\"num\":\"0\",\"cus10\":\"\",\"code5\":\"\",\"cusnum\":\"\",\"cus9\":\"\",\"cus7\":\"\",\"cusdata\":\"\",\"cus8\":\"\",\"cus5\":\"\",\"cus6\":\"\",\"cus3\":\"\",\"cus4\":\"\",\"cus1\":\"\",\"cus2\":\"\"},{\"code4\":\"\",\"code3\":\"https://clickhtml.kro.kr\",\"code2\":\"\",\"code\":\"\\u003cfont face\\u003d\\\"\\\"\\u003e\\u003cp\\u003e \\u003ca href \\u003d \\\"https://clickhtml.kro.kr\\\" target \\u003d \\\"_self\\\"\\u003eVersion 1.0 Release | by Blackcats4567\\u003c/a\\u003e \\u003c/h1\\u003e\",\"data\":\"Version 1.0 Release | by Blackcats4567\",\"num\":\"1\",\"cus10\":\"\",\"code5\":\"\",\"cus9\":\"\",\"cus7\":\"\",\"cusdata\":\"\",\"cus8\":\"\",\"cus5\":\"\",\"cus6\":\"\",\"cus3\":\"\",\"cus4\":\"\",\"cus1\":\"\",\"cus2\":\"\"},{\"code4\":\"\",\"code3\":\"\",\"code2\":\"\",\"code\":\"\\u003c/body\\u003e\",\"data\":\"\",\"num\":\"5\",\"cus10\":\"\",\"code5\":\"\",\"cusnum\":\"\",\"cus9\":\"\",\"cus7\":\"\",\"cusdata\":\"\",\"cus8\":\"\",\"cus5\":\"\",\"cus6\":\"\",\"cus3\":\"\",\"cus4\":\"\",\"cus1\":\"\",\"cus2\":\"\"}]",
        "rank" : "OWNER",
        "time" : "04/23/2020 01:18:31 PM",
        "title" : "Youtube BGM list (1.1)",
        "type" : "1",
        "uploader" : "lee25802733@gmail.com"
}
]
